README.md
setup.cfg
setup.py
ProTiler/ProTiler_call.py
ProTiler/ProTiler_predict.py
ProTiler/__init__.py
ProTiler/filepath.py
ProTiler/profiler.py
ProTiler.egg-info/PKG-INFO
ProTiler.egg-info/SOURCES.txt
ProTiler.egg-info/dependency_links.txt
ProTiler.egg-info/requires.txt
ProTiler.egg-info/top_level.txt
ProTiler.egg-info/zip-safe
ProTiler/StaticFiles/Pfam.py
ProTiler/StaticFiles/Pfam_genome_dic
ProTiler/StaticFiles/ProTiler_TGUH.R
ProTiler/StaticFiles/SVM_Input.csv
ProTiler/StaticFiles/ac_dic
ProTiler/StaticFiles/con_kde_dic
ProTiler/StaticFiles/domain_revision.py
ProTiler/StaticFiles/exons_dic
ProTiler/StaticFiles/exons_dict
ProTiler/StaticFiles/filepath.py
ProTiler/StaticFiles/filepath.pyc
ProTiler/StaticFiles/isoform_genome_dic
ProTiler/StaticFiles/me_dic
ProTiler/StaticFiles/pfam_genomic_position.txt
ProTiler/StaticFiles/po_dic
ProTiler/StaticFiles/sift_genome_dic
ProTiler/StaticFiles/ss_genome_dic_new
ProTiler/StaticFiles/ub_dic
bin/protiler
protiler.egg-info/PKG-INFO
protiler.egg-info/SOURCES.txt
protiler.egg-info/dependency_links.txt
protiler.egg-info/requires.txt
protiler.egg-info/top_level.txt
protiler.egg-info/zip-safe