Metadata-Version: 2.1
Name: protiler
Version: 1.0.2
Summary: Call HS regions from CRISPR tiling screen data and predict HS region from common protein features
Home-page: https://github.com/MDhewei/ProTiler-1.0.0
Author: Wei He
Author-email: whe3@mdanderson.org
License: UNKNOWN
Platform: UNKNOWN
